pydamic/PYDAMIC.py
pydamic/__init__.py
pydamic-0.2.10.dist-info/METADATA
pydamic-0.2.10.dist-info/WHEEL
pydamic-0.2.10.dist-info/top_level.txt
pydamic-0.2.10.dist-info/RECORD
